mdforge/__init__.py
mdforge/_norm.py
mdforge/_utils.py
mdforge/container.py
mdforge/document.py
mdforge/element.py
mdforge/elements/__init__.py
mdforge/elements/_image.py
mdforge/elements/block/__init__.py
mdforge/elements/block/basic.py
mdforge/elements/block/lists/__init__.py
mdforge/elements/block/lists/definition.py
mdforge/elements/block/lists/item.py
mdforge/elements/block/section.py
mdforge/elements/block/table/__init__.py
mdforge/elements/block/table/_context.py
mdforge/elements/block/table/_flavors/flavors.py
mdforge/elements/block/table/_flavors/frame/__init__.py
mdforge/elements/block/table/_flavors/frame/context.py
mdforge/elements/block/table/_flavors/frame/variant.py
mdforge/elements/block/table/_flavors/frame/variants.py
mdforge/elements/block/table/_flavors/list/__init__.py
mdforge/elements/block/table/_params.py
mdforge/elements/block/table/_variant.py
mdforge/elements/block/table/_vcell.py
mdforge/elements/block/table/cell.py
mdforge/elements/block/table/table.py
mdforge/elements/block/text.py
mdforge/elements/inline/__init__.py
mdforge/elements/inline/basic.py
mdforge/elements/inline/text.py
mdforge/exceptions.py
mdforge/types.py
mdforge-0.2.1.dist-info/LICENSE
mdforge-0.2.1.dist-info/METADATA
mdforge-0.2.1.dist-info/WHEEL
mdforge-0.2.1.dist-info/RECORD
